MANIFEST.in
README.md
asterisk-dump
asterisk-recover
py-asterisk
setup.py
Asterisk/CLI.py
Asterisk/Config.py
Asterisk/Logging.py
Asterisk/Manager.py
Asterisk/Util.py
Asterisk/__init__.py
py_Asterisk.egg-info/PKG-INFO
py_Asterisk.egg-info/SOURCES.txt
py_Asterisk.egg-info/dependency_links.txt
py_Asterisk.egg-info/pbr.json
py_Asterisk.egg-info/top_level.txt