Metadata-Version: 1.0
Name: py-Asterisk
Version: 0.5.18
Summary: Asterisk Manager API Python interface.
Home-page: https://github.com/jeansch/py-asterisk/
Author: David Wilson
Author-email: dw@botanicus.net
License: MIT
Platform: UNKNOWN
